guillotina/__init__.py
guillotina/_cache.py
guillotina/_settings.py
guillotina/addons.py
guillotina/annotations.py
guillotina/asgi.py
guillotina/async_util.py
guillotina/blob.py
guillotina/browser.py
guillotina/const.py
guillotina/constraintypes.py
guillotina/content.py
guillotina/contentapi.py
guillotina/contentnegotiation.py
guillotina/cors.py
guillotina/directives.py
guillotina/entrypoint.py
guillotina/error_reasons.py
guillotina/event.py
guillotina/events.py
guillotina/exc_resp.py
guillotina/exceptions.py
guillotina/glogging.py
guillotina/gtypes.py
guillotina/i18n.py
guillotina/languages.py
guillotina/metrics.py
guillotina/permissions.py
guillotina/profile.py
guillotina/py.typed
guillotina/registry.py
guillotina/renderers.py
guillotina/request.py
guillotina/response.py
guillotina/routes.py
guillotina/subscribers.py
guillotina/task_vars.py
guillotina/test_package.py
guillotina/testing.py
guillotina/transactions.py
guillotina/traversal.py
guillotina/writable.py
guillotina/api/__init__.py
guillotina/api/addons.py
guillotina/api/aggregation.py
guillotina/api/app.py
guillotina/api/behaviors.py
guillotina/api/container.py
guillotina/api/content.py
guillotina/api/dynamic.py
guillotina/api/files.py
guillotina/api/login.py
guillotina/api/metadata.py
guillotina/api/registry.py
guillotina/api/search.py
guillotina/api/service.py
guillotina/api/storage.py
guillotina/api/types.py
guillotina/api/user.py
guillotina/api/vocabularies.py
guillotina/api/ws.py
guillotina/auth/__init__.py
guillotina/auth/extractors.py
guillotina/auth/groups.py
guillotina/auth/recaptcha.py
guillotina/auth/role.py
guillotina/auth/users.py
guillotina/auth/utils.py
guillotina/auth/validators.py
guillotina/behaviors/__init__.py
guillotina/behaviors/attachment.py
guillotina/behaviors/dublincore.py
guillotina/behaviors/dynamic.py
guillotina/behaviors/instance.py
guillotina/behaviors/properties.py
guillotina/catalog/__init__.py
guillotina/catalog/catalog.py
guillotina/catalog/index.py
guillotina-7.0.6.dist-info/licenses/LICENSE
guillotina-7.0.6.dist-info/METADATA
guillotina-7.0.6.dist-info/WHEEL
guillotina-7.0.6.dist-info/entry_points.txt
guillotina-7.0.6.dist-info/top_level.txt
guillotina-7.0.6.dist-info/RECORD
