Metadata-Version: 2.4
Name: guillotina
Version: 7.0.6
Summary: asyncio REST API Resource database
Home-page: https://github.com/plone/guillotina
Author: Ramon Navarro Bosch & Nathan Van Gheem
Author-email: ramon@plone.org
License: BSD
Keywords: asyncio,REST,Framework,transactional,asgi
Classifier: License :: OSI Approved :: BSD License
Classifier: Intended Audience :: Developers
Classifier: Topic :: Internet :: WWW/HTTP
Classifier: Programming Language :: Python :: 3.7
Classifier: Programming Language :: Python :: 3.8
Classifier: Programming Language :: Python :: 3.9
Classifier: Programming Language :: Python :: 3.10
Classifier: Topic :: Software Development :: Libraries :: Python Modules
Requires-Python: >=3.7.0
License-File: LICENSE
Requires-Dist: uvicorn
Requires-Dist: websockets
Requires-Dist: jsonschema==2.6.0
Requires-Dist: python-dateutil
Requires-Dist: pycryptodome
Requires-Dist: jwcrypto
Requires-Dist: setuptools
Requires-Dist: orjson<4,>=3
Requires-Dist: zope.interface
Requires-Dist: pyjwt
Requires-Dist: asyncpg
Requires-Dist: cffi
Requires-Dist: PyYAML>=5.1
Requires-Dist: lru-dict
Requires-Dist: mypy_extensions
Requires-Dist: argon2-cffi
Requires-Dist: backoff
Requires-Dist: multidict
Requires-Dist: typing_extensions
Requires-Dist: watchfiles>=0.16.1
Provides-Extra: test
Requires-Dist: pytest<6.3.0,>=3.8.0; extra == "test"
Requires-Dist: docker==7.1.0; extra == "test"
Requires-Dist: backoff; extra == "test"
Requires-Dist: psycopg2-binary; extra == "test"
Requires-Dist: pytest-asyncio<=0.13.0; extra == "test"
Requires-Dist: pytest-cov; extra == "test"
Requires-Dist: coverage>=4.0.3; extra == "test"
Requires-Dist: pytest-docker-fixtures; extra == "test"
Requires-Dist: pytest-rerunfailures<=10.1; extra == "test"
Requires-Dist: async-asgi-testclient<2.0.0; extra == "test"
Requires-Dist: openapi-spec-validator==0.2.9; extra == "test"
Requires-Dist: aiohttp<4.0.0,>=3.0.0; extra == "test"
Requires-Dist: asyncmock; extra == "test"
Requires-Dist: prometheus-client; extra == "test"
Provides-Extra: docs
Requires-Dist: async-asgi-testclient<2.0.0; extra == "docs"
Requires-Dist: sphinx; extra == "docs"
Requires-Dist: recommonmark; extra == "docs"
Requires-Dist: sphinxcontrib-httpdomain; extra == "docs"
Requires-Dist: sphinxcontrib-httpexample; extra == "docs"
Requires-Dist: sphinx-guillotina-theme; extra == "docs"
Requires-Dist: sphinx-autodoc-typehints; extra == "docs"
Provides-Extra: testdata
Requires-Dist: aiohttp<3.6.0,>=3.0.0; python_version < "3.8" and extra == "testdata"
Requires-Dist: aiohttp<4.0.0,>=3.6.0; python_version >= "3.8" and extra == "testdata"
Provides-Extra: redis
Requires-Dist: redis>=4.3.0; extra == "redis"
Provides-Extra: mailer
Requires-Dist: html2text>=2018.1.9; extra == "mailer"
Requires-Dist: aiosmtplib>=1.0.6; extra == "mailer"
Provides-Extra: memcached
Requires-Dist: emcache; extra == "memcached"
Provides-Extra: validation
Requires-Dist: pytz==2020.1; extra == "validation"
Provides-Extra: recaptcha
Requires-Dist: aiohttp<4; extra == "recaptcha"
Dynamic: author
Dynamic: author-email
Dynamic: classifier
Dynamic: description
Dynamic: home-page
Dynamic: keywords
Dynamic: license
Dynamic: license-file
Dynamic: provides-extra
Dynamic: requires-dist
Dynamic: requires-python
Dynamic: summary
